oauth42/__init__.py
oauth42/__version__.py
oauth42/client.py
oauth42/examples/fastapi_example/main.py
oauth42/examples/flask_example/app.py
oauth42/middleware/__init__.py
oauth42/middleware/fastapi.py
oauth42/middleware/flask.py
oauth42/oauth42/__init__.py
oauth42/oauth42/__version__.py
oauth42/oauth42/client.py
oauth42/oauth42/py.typed
oauth42/oauth42/types_/__init__.py
oauth42/oauth42/types_/exceptions.py
oauth42/oauth42/types_/models.py
oauth42/oauth42/utils/__init__.py
oauth42/oauth42/utils/crypto.py
oauth42/oauth42/utils/discovery.py
oauth42/tests/__init__.py
oauth42/tests/conftest.py
oauth42/tests/test_client.py
oauth42/tests/test_config.py
oauth42/tests/test_crypto.py
oauth42/tests/test_discovery.py
oauth42/tests/test_exceptions.py
oauth42/tests/test_models.py
oauth42/tests/integration/__init__.py
oauth42/tests/integration/test_oauth42_integration.py
oauth42/types/__init__.py
oauth42/types/exceptions.py
oauth42/types/models.py
oauth42/types_/__init__.py
oauth42/types_/exceptions.py
oauth42/types_/models.py
oauth42/utils/__init__.py
oauth42/utils/crypto.py
oauth42/utils/discovery.py
oauth42-0.2.1.dist-info/licenses/LICENSE
oauth42-0.2.1.dist-info/METADATA
oauth42-0.2.1.dist-info/WHEEL
oauth42-0.2.1.dist-info/entry_points.txt
oauth42-0.2.1.dist-info/top_level.txt
oauth42-0.2.1.dist-info/RECORD
