Metadata-Version: 2.4
Name: oauth42
Version: 0.2.1
Summary: Official OAuth42 SDK for Python applications
Author-email: OAuth42 Team <support@oauth42.com>
License: Proprietary
Project-URL: Homepage, https://oauth42.com
Project-URL: Documentation, https://docs.oauth42.com/sdk/python
Project-URL: Repository, https://github.com/devxpod/oauth42
Project-URL: Issues, https://github.com/devxpod/oauth42/issues
Keywords: oauth2,oidc,authentication,fastapi,flask,django
Classifier: Development Status :: 4 - Beta
Classifier: Intended Audience :: Developers
Classifier: License :: Other/Proprietary License
Classifier: Programming Language :: Python :: 3
Classifier: Programming Language :: Python :: 3.12
Classifier: Programming Language :: Python :: 3.13
Classifier: Framework :: FastAPI
Classifier: Framework :: Flask
Classifier: Framework :: Django
Classifier: Topic :: Internet :: WWW/HTTP :: Session
Classifier: Topic :: Security
Classifier: Typing :: Typed
Requires-Python: >=3.12
License-File: LICENSE
Requires-Dist: httpx>=0.24.0
Requires-Dist: pydantic>=2.0.0
Requires-Dist: PyJWT>=2.8.0
Requires-Dist: cryptography>=41.0.0
Requires-Dist: python-dotenv>=1.0.0
Provides-Extra: fastapi
Requires-Dist: fastapi>=0.100.0; extra == "fastapi"
Requires-Dist: python-multipart>=0.0.6; extra == "fastapi"
Provides-Extra: flask
Requires-Dist: Flask>=2.3.0; extra == "flask"
Requires-Dist: Flask-Session>=0.5.0; extra == "flask"
Provides-Extra: django
Requires-Dist: Django>=4.2.0; extra == "django"
Provides-Extra: dev
Requires-Dist: pytest>=7.4.0; extra == "dev"
Requires-Dist: pytest-asyncio>=0.21.0; extra == "dev"
Requires-Dist: pytest-cov>=4.1.0; extra == "dev"
Requires-Dist: mypy>=1.5.0; extra == "dev"
Requires-Dist: ruff>=0.1.0; extra == "dev"
Requires-Dist: black>=23.0.0; extra == "dev"
Requires-Dist: pre-commit>=3.3.0; extra == "dev"
Dynamic: license-file
